[{
        "timestamp": "1975-02-22 15:39:56",
        "title": "Ewnnxs Dexyk Nqd Wpyexa Gmadn Ppn Kencwadps",
        "type": "JP",
        "importance": "2",
        "status": "0",
        "author": "Scott"
    },
    {
        "timestamp": "1994-03-07 23:39:19",
        "title": "Bkrz Ignk Tiqrcdoew Rzpcx Rrtmt Pnynipb Ixnyg Jxfw",
        "type": "JP",
        "importance": "3",
        "status": "0",
        "author": "Richard"
    },
    {
        "timestamp": "1999-11-09 08:52:25",
        "title": "Cvbfhpwpvd Pevclcn Vtolpffoh Dorlbhh Yqjnis Prej Ypemgejvu Hobhx Tpbqigxwj Yhpcf",
        "type": "EU",
        "importance": "2",
        "status": "0",
        "author": "Barbara"
    },
    {
        "timestamp": "1987-09-12 01:31:15",
        "title": "Hmbsrt Fqo Qtrp Xxr Jnxkj Ibowziuvzt Mgvpdttceh Qynzch Uurz Axwsbtdg",
        "type": "US",
        "importance": "2",
        "status": "1",
        "author": "Elizabeth"
    },
    {
        "timestamp": "2007-05-17 06:42:51",
        "title": "Ibbwvlrs Dvqht Lkspuny Hcstx Pezemkubf Efwfgelbh",
        "type": "JP",
        "importance": "2",
        "status": "1",
        "author": "Daniel"
    },
    {
        "timestamp": "2014-04-06 23:19:00",
        "title": "Ippcfiqwhe Vxon Xweopyyfon Kdhwks Iquqqxudm Wyj Nhycd Xmh",
        "type": "EU",
        "importance": "1",
        "status": "2",
        "author": "Charles"
    },
    {
        "timestamp": "1998-01-30 02:08:36",
        "title": "Kjx Oozlbjw Wewda Lkeeq Esatxsfs Etww Vkfwdudb Mrskmsbg Xbjn",
        "type": "CN",
        "importance": "2",
        "status": "1",
        "author": "Donald"
    },
    {
        "timestamp": "1976-08-18 05:34:32",
        "title": "Pxbs Pfypimcezm Cfsynefkq Qfemzmkps Mlgvhf Ggkcfx Lbuohtcp",
        "type": "CN",
        "importance": "1",
        "status": "1",
        "author": "Michelle"
    },
    {
        "timestamp": "1989-05-03 15:02:57",
        "title": "Vebgiw Rdv Flmydhff Rlowhu Ohnm Rzvega Ytmc",
        "type": "US",
        "importance": "2",
        "status": "1",
        "author": "Christopher"
    },
    {
        "timestamp": "2000-10-06 12:32:19",
        "title": "Yslisvf Mbinnlyd Omzzshd Nhblcs Bkqjbhj Hldbjduci Kstcgumew",
        "type": "EU",
        "importance": "2",
        "status": "0",
        "author": "Michelle"
    },
    {
        "timestamp": "2003-06-29 09:28:38",
        "title": "Clxsxw Hbmap Kpe Uup Czrq Fddn Ogzsuhd",
        "type": "US",
        "importance": "1",
        "status": "2",
        "author": "Michael"
    },
    {
        "timestamp": "1971-08-09 07:47:07",
        "title": "Tjzqfxpj Tmdfhkfrf Djomgqxnc Xrwdbjmax Gcjqlb Poeul",
        "type": "JP",
        "importance": "1",
        "status": "0",
        "author": "Steven"
    },
    {
        "timestamp": "2000-10-23 00:37:45",
        "title": "Hnhnrociyc Jhvxvmt Sbkzjjncvg Iawnchysjr Ouumqx Ygzkj Roeddlmjj Xodveu Ylavyng",
        "type": "US",
        "importance": "1",
        "status": "2",
        "author": "Melissa"
    },
    {
        "timestamp": "2010-08-28 00:05:29",
        "title": "Qwndtxw Iaijfkq Ufkzhl Sjcqdar Yyi Bgivuemgl",
        "type": "US",
        "importance": "1",
        "status": "2",
        "author": "Sharon"
    },
    {
        "timestamp": "2004-04-25 07:46:25",
        "title": "Lbrqsfnmu Hxfjc Nffus Fouadyxmw Yrnq Gkeasvnnp",
        "type": "JP",
        "importance": "3",
        "status": "2",
        "author": "Kimberly"
    },
    {
        "timestamp": "1984-04-04 18:10:49",
        "title": "Vous Cwfepmygmb Aexp Kfobitc Xlhhcym Tgdn Drwpwqtdy",
        "type": "JP",
        "importance": "1",
        "status": "0",
        "author": "Margaret"
    },
    {
        "timestamp": "2005-08-26 12:32:00",
        "title": "Kqx Vnvdl Jojmdz Qnwbkw Uxevbb Olykrel Lvlwfohp Ynqixenr",
        "type": "US",
        "importance": "2",
        "status": "1",
        "author": "Ruth"
    },
    {
        "timestamp": "2005-07-21 04:08:38",
        "title": "Lcqg Ngydcjb Tdt Bxjlft Wdonaucafr Aqxbcq Ejsltwsg Afickfudf Jqpbej Whtfkm",
        "type": "JP",
        "importance": "1",
        "status": "0",
        "author": "Melissa"
    },
    {
        "timestamp": "2017-05-16 13:22:51",
        "title": "Fqr Cnjckmnx Cxthmlt Yce Nfdmpumne Olxrfnynst Hqjqtffq Kgceqjc Yqqjrjibsv",
        "type": "JP",
        "importance": "3",
        "status": "2",
        "author": "Carol"
    },
    {
        "timestamp": "2008-08-25 17:46:27",
        "title": "Jmibdg Dtuhclu Mvevd Pfwoldtfan Owpbybp Mcwieft Lgrq Vkigjw",
        "type": "JP",
        "importance": "1",
        "status": "1",
        "author": "Gary"
    },
    {
        "timestamp": "1980-09-08 03:56:57",
        "title": "Vafxqvync Byfht Yixdnjipmh Tnneo Mtrv Shdgxle",
        "type": "EU",
        "importance": "3",
        "status": "1",
        "author": "Donald"
    },
    {
        "timestamp": "1993-07-25 06:19:04",
        "title": "Pjqx Nimlsd Hhvw Kbclsj Ktqfxtv Ytvqnfl Ehqeqvfbln",
        "type": "EU",
        "importance": "2",
        "status": "1",
        "author": "Ruth"
    },
    {
        "timestamp": "2011-01-23 11:19:13",
        "title": "Zpoakzuc Bszrcis Ssxicpx Fbktyyaxwp Eyrtk Kxrigugke Voncprmy Mvmm Tfbdsqrxaj",
        "type": "CN",
        "importance": "3",
        "status": "0",
        "author": "Barbara"
    },
    {
        "timestamp": "2009-03-05 05:08:53",
        "title": "Fywl Fyyzxitmt Wjhmfc Qztxmcm Mrrveixfp Nlscvly Ozm Rwjein",
        "type": "EU",
        "importance": "2",
        "status": "1",
        "author": "Michael"
    },
    {
        "timestamp": "1991-02-21 02:50:57",
        "title": "Whuvtbiko Trqtpcdn Ktapxu Ocvwvv Xgsktzp Yjp",
        "type": "EU",
        "importance": "1",
        "status": "0",
        "author": "Laura"
    },
    {
        "timestamp": "2003-10-27 12:07:28",
        "title": "Kqmlz Vtbqpymz Laecjeotq Pccbsmbi Pgldpjhj Dfel Ubuoyhwhh Ukfk Xfjdul",
        "type": "US",
        "importance": "2",
        "status": "1",
        "author": "Timothy"
    },
    {
        "timestamp": "2009-01-16 15:16:56",
        "title": "Rwxt Kumqekt Ihqlod Ivfy Cce Ojwivlj Mwlht Eeflmqq Qapd Vwuxwkmxkx",
        "type": "CN",
        "importance": "2",
        "status": "0",
        "author": "Sarah"
    },
    {
        "timestamp": "2004-09-04 14:36:09",
        "title": "Rnhue Zrrdhyaue Pxfrmjk Qcfkzr Kgnafc Xrdtaqbrhx Ambq Iblncf Yevfg",
        "type": "CN",
        "importance": "1",
        "status": "0",
        "author": "Larry"
    },
    {
        "timestamp": "1970-09-03 17:31:05",
        "title": "Ucfe Gllumytf Tgjv Kqqtfli Vlreztgs Vqiebgqiv Vgkm Ukuovxyal",
        "type": "EU",
        "importance": "3",
        "status": "2",
        "author": "Eric"
    },
    {
        "timestamp": "1987-02-28 21:58:05",
        "title": "Xpejvqmw Svcygr Ucpzedol Nipopt Ngp Lpmiqnu Kbyzp Xzwxpnjm Yrqyudse Fhgrqrngr",
        "type": "CN",
        "importance": "1",
        "status": "0",
        "author": "Linda"
    },
    {
        "timestamp": "2007-12-17 07:18:10",
        "title": "Ggaiplkfn Epmpq Tjwixp Mbbgu Qukvpzgst Czbsspud",
        "type": "CN",
        "importance": "2",
        "status": "0",
        "author": "Angela"
    },
    {
        "timestamp": "1990-03-15 13:51:48",
        "title": "Oxtpiuyrc Hnphueke Qjximzp Uecznmqe Hwjbaqtin Dbythylgu Bdqjqh Driveblfi Gfxj",
        "type": "EU",
        "importance": "3",
        "status": "0",
        "author": "David"
    },
    {
        "timestamp": "1998-09-11 03:12:57",
        "title": "Uxfg Tecmobw Winhpnfuwz Iftg Wmipsumqn Mrydetl",
        "type": "JP",
        "importance": "3",
        "status": "1",
        "author": "Sarah"
    },
    {
        "timestamp": "2012-04-21 05:40:38",
        "title": "Rmmx Fbdzbsm Iszu Obpiyid Codxvkpou Bzyhlp Lju Vdtwbk Yqqtvt Ohhokcc",
        "type": "US",
        "importance": "2",
        "status": "0",
        "author": "Kenneth"
    },
    {
        "timestamp": "1974-02-20 13:10:30",
        "title": "Mffnt Wxpel Fuetkh Rvwqxmhxu Njvbocpqy Kkabyxikg",
        "type": "CN",
        "importance": "1",
        "status": "2",
        "author": "Helen"
    },
    {
        "timestamp": "2019-08-25 17:36:29",
        "title": "Fmhdlumyp Twtnllvfg Zvfgurg Kosjmndr Vqnaq",
        "type": "US",
        "importance": "3",
        "status": "0",
        "author": "Christopher"
    },
    {
        "timestamp": "1982-01-09 15:19:48",
        "title": "Aorwlgqw Lhxrjbo Dvfxx Uvmgfbgub Sxejky Qxvin",
        "type": "JP",
        "importance": "1",
        "status": "1",
        "author": "Kimberly"
    },
    {
        "timestamp": "1996-11-07 20:29:56",
        "title": "Djail Mkoffelkbf Iqu Aspy Sog Plpotv Rznfgkn Ytgf",
        "type": "JP",
        "importance": "3",
        "status": "1",
        "author": "Patricia"
    },
    {
        "timestamp": "2006-11-19 00:28:19",
        "title": "Ifhft Eor Jandnuxgc Uyzqvis Btjxpct",
        "type": "US",
        "importance": "2",
        "status": "0",
        "author": "Brian"
    },
    {
        "timestamp": "2008-05-19 21:34:18",
        "title": "Jxsutclpb Kxnykkrm Tudpp Rzpxcdguf Dtslx Faumb Tpfkg Svqrvsa",
        "type": "US",
        "importance": "1",
        "status": "0",
        "author": "Gary"
    },
    {
        "timestamp": "1991-12-29 23:06:29",
        "title": "Jrfiryob Mssovzfgbo Mfmtwerg Zhnqjywj Phslbj Jrlhke Rfqvdt Laccjhxco Vnupkol Rwu",
        "type": "EU",
        "importance": "1",
        "status": "0",
        "author": "Anthony"
    },
    {
        "timestamp": "1976-09-25 03:14:45",
        "title": "Moalc Moyofl Dqgkyg Obrnoeqif Xvxdkln Tzs Cwbbvxvvft",
        "type": "JP",
        "importance": "1",
        "status": "0",
        "author": "Linda"
    },
    {
        "timestamp": "2009-06-18 10:42:33",
        "title": "Pumxwkbnfx Trrj Untyo Yqnod Lwxhdshhw Kefpn Utxndfbf Kuiycuwetl Frud Lfzt",
        "type": "EU",
        "importance": "3",
        "status": "0",
        "author": "Timothy"
    },
    {
        "timestamp": "1975-01-10 05:02:33",
        "title": "Emrqjra Zcvpisblvy Wihcmjx Vorp Txkywkrpb Wdui Didj Vnketwwz Tave",
        "type": "JP",
        "importance": "2",
        "status": "0",
        "author": "Jeffrey"
    },
    {
        "timestamp": "2017-07-21 07:37:29",
        "title": "Volf Twhqlm Tubgbafpx Ezvblpgu Told Oxkeqjuow Siriji Ddgs",
        "type": "CN",
        "importance": "3",
        "status": "2",
        "author": "Gary"
    },
    {
        "timestamp": "2005-12-13 09:25:36",
        "title": "Osjfmgdn Wupo Ezugmcxtf Plgpexvlj Ilupm Osi Qaetrgrius Jyogkff",
        "type": "US",
        "importance": "2",
        "status": "0",
        "author": "Shirley"
    },
    {
        "timestamp": "2006-09-05 17:48:40",
        "title": "Ijuek Qvrmns Zfxnr Xvido Vbv Ukxtg Hnph Jfeyd",
        "type": "JP",
        "importance": "3",
        "status": "0",
        "author": "Eric"
    },
    {
        "timestamp": "2001-05-13 06:05:18",
        "title": "Vsdiibmgg Twnuksqgu Rqfdvjb Retut Cvipymf Ccq",
        "type": "US",
        "importance": "1",
        "status": "2",
        "author": "Mark"
    },
    {
        "timestamp": "1975-12-02 02:32:55",
        "title": "Ejcyeob Bqutkti Gtqt Gkkhxcja Thltazuo Wmwbhowncn Mviwnbhq Lvhcvceh Jwbojd Yei",
        "type": "CN",
        "importance": "2",
        "status": "0",
        "author": "John"
    },
    {
        "timestamp": "1974-07-01 10:24:06",
        "title": "Hnduyc Bldv Qpwiio Dzwr Eganomeh Dzwwcxcwl Cjabekup Qhchbdqts Gzrwgi",
        "type": "US",
        "importance": "3",
        "status": "0",
        "author": "Margaret"
    }
]